src/rtl/wallace_mult_8bit.v
// 8x8 Wallace Tree Multiplier
// Pipelined into 3 stages using registers
// Written in behavioral style 

module wallace_mult_8bit(
    input clk,
    input rst_n,        // reset, active low
    input valid_in,
    input [7:0] a,
    input [7:0] b,
    output reg valid_out,
    output reg [15:0] product
);

    // ---------------------------------------------------------
    // STAGE 1
    // Make all 8 partial products and add some of them together
    // ---------------------------------------------------------

    reg [15:0] pp0, pp1, pp2, pp3, pp4, pp5, pp6, pp7;

    // these will hold the result after stage 1
    reg [15:0] row1_0, row1_1, row1_2, row1_3, row1_4, row1_5;
    reg stage1_valid;

    // temporary variables used to add 3 rows together
    reg [15:0] sum_temp, carry_temp;

    always @(posedge clk or negedge rst_n) begin
        if (!rst_n) begin
            row1_0 <= 0;
            row1_1 <= 0;
            row1_2 <= 0;
            row1_3 <= 0;
            row1_4 <= 0;
            row1_5 <= 0;
            stage1_valid <= 0;
        end else begin

            // make the 8 partial products
            // if bit i of b is 1, shift a left by i, else 0
            if (b[0] == 1) pp0 = a; else pp0 = 0;
            if (b[1] == 1) pp1 = a << 1; else pp1 = 0;
            if (b[2] == 1) pp2 = a << 2; else pp2 = 0;
            if (b[3] == 1) pp3 = a << 3; else pp3 = 0;
            if (b[4] == 1) pp4 = a << 4; else pp4 = 0;
            if (b[5] == 1) pp5 = a << 5; else pp5 = 0;
            if (b[6] == 1) pp6 = a << 6; else pp6 = 0;
            if (b[7] == 1) pp7 = a << 7; else pp7 = 0;

            // add the first 3 partial products together (like a full adder)
            sum_temp   = pp0 ^ pp1 ^ pp2;
            carry_temp = (pp0 & pp1) | (pp1 & pp2) | (pp0 & pp2);
            carry_temp = carry_temp << 1;
            row1_0 <= sum_temp;
            row1_1 <= carry_temp;

            // add the next 3 partial products together
            sum_temp   = pp3 ^ pp4 ^ pp5;
            carry_temp = (pp3 & pp4) | (pp4 & pp5) | (pp3 & pp5);
            carry_temp = carry_temp << 1;
            row1_2 <= sum_temp;
            row1_3 <= carry_temp;

            // last 2 partial products just pass through to next stage
            row1_4 <= pp6;
            row1_5 <= pp7;

            stage1_valid <= valid_in;
        end
    end


    // ---------------------------------------------------------
    // STAGE 2
    // Keep adding the 6 rows from stage 1 down to just 2 rows
    // ---------------------------------------------------------

    reg [15:0] row2_sum, row2_carry;
    reg stage2_valid;

    reg [15:0] sumA, carryA;
    reg [15:0] sumB, carryB;
    reg [15:0] sumC, carryC;

    always @(posedge clk or negedge rst_n) begin
        if (!rst_n) begin
            row2_sum   <= 0;
            row2_carry <= 0;
            stage2_valid <= 0;
        end else begin

            // add rows 0,1,2 from stage 1
            sumA   = row1_0 ^ row1_1 ^ row1_2;
            carryA = (row1_0 & row1_1) | (row1_1 & row1_2) | (row1_0 & row1_2);
            carryA = carryA << 1;

            // add rows 3,4,5 from stage 1
            sumB   = row1_3 ^ row1_4 ^ row1_5;
            carryB = (row1_3 & row1_4) | (row1_4 & row1_5) | (row1_3 & row1_5);
            carryB = carryB << 1;

            // now we have 4 rows: sumA, carryA, sumB, carryB
            // add 3 of them together
            sumC   = sumA ^ carryA ^ sumB;
            carryC = (sumA & carryA) | (carryA & sumB) | (sumA & sumB);
            carryC = carryC << 1;

            // now combine sumC with the leftover row (carryB)
            // this is just like a half adder (only 2 inputs left)
            row2_sum   <= sumC ^ carryB;
            row2_carry <= carryC + ((sumC & carryB) << 1);

            stage2_valid <= stage1_valid;
        end
    end


    // ---------------------------------------------------------
    // STAGE 3
    // Final addition of the last 2 rows to get the answer
    // ---------------------------------------------------------

    always @(posedge clk or negedge rst_n) begin
        if (!rst_n) begin
            product   <= 0;
            valid_out <= 0;
        end else begin
            product   <= row2_sum + row2_carry;  // regular addition
            valid_out <= stage2_valid;
        end
    end

endmodule

tb_wallace_mult_8bit.v
// Simple testbench for the 8x8 Wallace tree multiplier
// Just applies some test values and prints the result
// We check the answer by looking at the printed numbers

module tb_wallace_mult_8bit;

    reg clk;
    reg rst_n;
    reg valid_in;
    reg [7:0] a;
    reg [7:0] b;
    wire valid_out;
    wire [15:0] product;

    // connect the multiplier
    wallace_mult_8bit dut (
        .clk(clk),
        .rst_n(rst_n),
        .valid_in(valid_in),
        .a(a),
        .b(b),
        .valid_out(valid_out),
        .product(product)
    );

    // Toggle every 10 ns for a 20 ns total period = 50 MHz
    initial clk = 0;
    always #10 clk = ~clk;

    // print the answer every time valid_out goes high
    always @(posedge clk) begin
        if (valid_out == 1) begin
            $display("Time=%0t  ->  product = %0d", $time, product);
        end
    end

    initial begin
        // Specifies the name of the output VCD file
        $dumpfile("waveform.vcd"); 
        // 0 means dump all signals in the testbench and submodules
        $dumpvars(0, tb_wallace_mult_8bit); 
        
        // start with reset on
        rst_n = 0;
        valid_in = 0;
        a = 0;
        b = 0;

        // hold reset for a few clocks
        @(posedge clk);
        @(posedge clk);
        @(posedge clk);

        // release reset
        rst_n = 1;
        @(posedge clk);

        $display("Starting tests...");

        // Test 1: 3 x 5 = 15
        a = 3; b = 5; valid_in = 1;
        @(posedge clk);
        valid_in = 0;
        @(posedge clk);
        @(posedge clk);
        @(posedge clk);

        // Test 2: 10 x 10 = 100
        a = 10; b = 10; valid_in = 1;
        @(posedge clk);
        valid_in = 0;
        @(posedge clk);
        @(posedge clk);
        @(posedge clk);

        // Test 3: 255 x 255 = 65025 (biggest possible answer)
        a = 255; b = 255; valid_in = 1;
        @(posedge clk);
        valid_in = 0;
        @(posedge clk);
        @(posedge clk);
        @(posedge clk);

        // Test 4: 0 x 200 = 0
        a = 0; b = 200; valid_in = 1;
        @(posedge clk);
        valid_in = 0;
        @(posedge clk);
        @(posedge clk);
        @(posedge clk);

        // Test 5: 128 x 2 = 256
        a = 128; b = 2; valid_in = 1;
        @(posedge clk);
        valid_in = 0;
        @(posedge clk);
        @(posedge clk);
        @(posedge clk);

        // Test 6: send a few values back to back, no gaps
        a = 4; b = 4; valid_in = 1;     // 16
        @(posedge clk);
        a = 6; b = 7;                  // 42
        @(posedge clk);
        a = 9; b = 9;                  // 81
        @(posedge clk);
        valid_in = 0;
        a = 0;
        b = 0;

        // wait a bit for the last answers to come out
        @(posedge clk);
        @(posedge clk);
        @(posedge clk);
        @(posedge clk);

        $display("Tests done. Check the printed products above against:");
        $display("Expected: 15, 100, 65025, 0, 256, then 16, 42, 81");

        $finish;
    end

endmodule

src/rtl/waveform.vcd
$date
	Sun Jun 28 09:48:24 2026
$end
$version
	Icarus Verilog
$end
$timescale
	1s
$end
$scope module tb_wallace_mult_8bit $end
$var wire 1 ! valid_out $end
$var wire 16 " product [15:0] $end
$var reg 8 # a [7:0] $end
$var reg 8 $ b [7:0] $end
$var reg 1 % clk $end
$var reg 1 & rst_n $end
$var reg 1 ' valid_in $end
$scope module dut $end
$var wire 8 ( a [7:0] $end
$var wire 8 ) b [7:0] $end
$var wire 1 % clk $end
$var wire 1 & rst_n $end
$var wire 1 ' valid_in $end
$var reg 16 * carryA [15:0] $end
$var reg 16 + carryB [15:0] $end
$var reg 16 , carryC [15:0] $end
$var reg 16 - carry_temp [15:0] $end
$var reg 16 . pp0 [15:0] $end
$var reg 16 / pp1 [15:0] $end
$var reg 16 0 pp2 [15:0] $end
$var reg 16 1 pp3 [15:0] $end
$var reg 16 2 pp4 [15:0] $end
$var reg 16 3 pp5 [15:0] $end
$var reg 16 4 pp6 [15:0] $end
$var reg 16 5 pp7 [15:0] $end
$var reg 16 6 product [15:0] $end
$var reg 16 7 row1_0 [15:0] $end
$var reg 16 8 row1_1 [15:0] $end
$var reg 16 9 row1_2 [15:0] $end
$var reg 16 : row1_3 [15:0] $end
$var reg 16 ; row1_4 [15:0] $end
$var reg 16 < row1_5 [15:0] $end
$var reg 16 = row2_carry [15:0] $end
$var reg 16 > row2_sum [15:0] $end
$var reg 1 ? stage1_valid $end
$var reg 1 @ stage2_valid $end
$var reg 16 A sumA [15:0] $end
$var reg 16 B sumB [15:0] $end
$var reg 16 C sumC [15:0] $end
$var reg 16 D sum_temp [15:0] $end
$var reg 1 ! valid_out $end
$upscope $end
$upscope $end
$enddefinitions $end
$comment Show the parameter values. $end
$dumpall
$end
#0
$dumpvars
bx D
bx C
bx B
bx A
0@
0?
b0 >
b0 =
b0 <
b0 ;
b0 :
b0 9
b0 8
b0 7
b0 6
bx 5
bx 4
bx 3
bx 2
bx 1
bx 0
bx /
bx .
bx -
bx ,
bx +
bx *
b0 )
b0 (
0'
0&
0%
b0 $
b0 #
b0 "
0!
$end
#10
1%
#20
0%
#30
1%
#40
0%
#50
b0 ,
b0 C
b0 +
b0 B
b0 *
b0 A
b0 -
b0 D
b0 5
b0 4
b0 3
b0 2
b0 1
b0 0
b0 /
b0 .
1&
1%
#60
0%
#70
1?
b1111 7
b0 D
b1100 0
b11 .
1'
b101 $
b101 )
b11 #
b11 (
1%
#80
0%
#90
1@
b1111 >
0?
b1111 C
b1111 A
b0 D
0'
1%
#100
0%
#110
0@
1!
b1111 "
b1111 6
b0 D
1%
#120
0%
#130
0!
b0 D
1%
#140
0%
#150
1?
b1010000 9
b10100 7
b1010000 D
b1010000 1
b0 0
b10100 /
b0 .
1'
b1010 $
b1010 )
b1010 #
b1010 (
1%
#160
0%
#170
1@
b1100100 >
0?
b1100100 C
b100000 *
b1000100 A
b1010000 D
0'
1%
#180
0%
#190
0@
1!
b1100100 "
b1100100 6
b1010000 D
b100000 *
1%
#200
0%
#210
0!
b100000 *
b1010000 D
1%
#220
0%
#230
1?
b111111110000000 <
b11111111000000 ;
b1111111100000 :
b1011111101000 9
b1111111100 8
b1011111101 7
b1111111100000 -
b1011111101000 D
b111111110000000 5
b11111111000000 4
b1111111100000 3
b111111110000 2
b11111111000 1
b1111111100 0
b111111110 /
b11111111 .
b100000 *
1'
b11111111 $
b11111111 )
b11111111 #
b11111111 (
1%
#240
0%
#250
1@
b1100110011010000 =
b11000100110001 >
0?
b10111111010000 ,
b100111010110001 C
b111111110000000 +
b101111110100000 B
b11111111000 *
b1011011101001 A
b1111111100000 -
b1011111101000 D
0'
1%
#260
0%
#270
0@
1!
b1111111000000001 "
b1111111000000001 6
b1111111100000 -
b1011111101000 D
b10111111010000 ,
b111111110000000 +
b11111111000 *
1%
#280
0%
#290
0!
b10111111010000 ,
b111111110000000 +
b11111111000 *
b1111111100000 -
b1011111101000 D
1%
#300
0%
#310
1?
b0 <
b0 ;
b0 :
b0 9
b0 8
b0 7
b0 -
b0 D
b0 5
b0 4
b0 3
b0 2
b0 1
b0 0
b0 /
b0 .
b10111111010000 ,
b111111110000000 +
b11111111000 *
1'
b11001000 $
b11001000 )
b0 #
b0 (
1%
#320
0%
#330
1@
b0 =
b0 >
0?
b0 ,
b0 C
b0 +
b0 B
b0 *
b0 A
0'
1%
#340
0%
#350
0@
1!
b0 "
b0 6
1%
#360
0%
#370
0!
1%
#380
0%
#390
1?
b100000000 7
b0 D
b100000000 /
1'
b10 $
b10 )
b10000000 #
b10000000 (
1%
#400
0%
#410
1@
b100000000 >
0?
b100000000 C
b100000000 A
b0 D
0'
1%
#420
0%
#430
0@
1!
b100000000 "
b100000000 6
b0 D
1%
#440
0%
#450
0!
b0 D
1%
#460
0%
#470
1?
b10000 7
b0 D
b10000 0
b0 /
1'
b100 $
b100 )
b100 #
b100 (
1%
#480
0%
#490
1@
b10000 >
b11000 8
b10010 7
b10000 C
b10000 A
b0 -
b0 D
b11000 0
b1100 /
b110 .
b111 $
b111 )
b110 #
b110 (
1%
#500
0%
#510
b1001000 9
b0 8
b1001 7
b101010 >
1!
b10000 "
b10000 6
b1001000 D
b1001000 1
b0 0
b0 /
b1001 .
b101010 C
b100000 *
b1010 A
b1001 $
b1001 )
b1001 #
b1001 (
1%
#520
0%
#530
b101010 "
b101010 6
b1010001 >
0?
b0 9
b0 7
b1010001 C
b10000 *
b1000001 A
b0 D
b0 1
b0 .
b0 $
b0 )
b0 #
b0 (
0'
1%
#540
0%
#550
0@
b0 >
b1010001 "
b1010001 6
b0 C
b0 *
b0 A
1%
#560
0%
#570
0!
b0 "
b0 6
1%
